<?xml version='1.0' encoding='utf-8'?>
<score-partwise version="4.0">
  <movement-title>Music21 Fragment</movement-title>
  <identification>
    <creator type="composer">Music21</creator>
    <encoding>
      <encoding-date>2026-02-01</encoding-date>
      <software>music21 v.9.9.1</software>
    </encoding>
  </identification>
  <defaults>
    <scaling>
      <millimeters>7</millimeters>
      <tenths>40</tenths>
    </scaling>
  </defaults>
  <part-list>
    <score-part id="P1820c53d570cba7503cc9519d4c06343">
      <part-name>Piano</part-name>
      <part-abbreviation>Pno</part-abbreviation>
      <score-instrument id="I873d7ddcdbfbfefb63832531f4c59b0a">
        <instrument-name>Piano</instrument-name>
        <instrument-abbreviation>Pno</instrument-abbreviation>
      </score-instrument>
      <midi-instrument id="I873d7ddcdbfbfefb63832531f4c59b0a">
        <midi-channel>1</midi-channel>
        <midi-program>1</midi-program>
      </midi-instrument>
    </score-part>
  </part-list>
  
  <part id="P1820c53d570cba7503cc9519d4c06343">
    
    <measure implicit="no" number="1">
      <print>
        <system-layout>
          <system-margins>
            <left-margin>76.2</left-margin>
            <right-margin>0</right-margin>
          </system-margins>
          <top-system-distance>170</top-system-distance>
        </system-layout>
      </print>
      <attributes>
        <divisions>10080</divisions>
        <key>
          <fifths>2</fifths>
        </key>
        <time>
          <beats>3</beats>
          <beat-type>4</beat-type>
        </time>
        <clef><sign>G</sign><line>2</line></clef></attributes>
      <direction placement="above">
        <direction-type>
          <words default-x="-37.68" font-weight="bold" relative-x="-17.19" relative-y="21.74">Lent et douloureux</words>
        </direction-type>
      </direction>
      <direction placement="above">
        <direction-type>
          <words />
        </direction-type>
      </direction>
      <direction placement="above">
        <direction-type>
          <words />
        </direction-type>
        <sound tempo="54" />
      </direction>
      <direction placement="below">
        <direction-type>
          <dynamics default-x="6.5" default-y="-40" relative-x="7.5" relative-y="-33.91">
            <pp />
          </dynamics>
        </direction-type>
        <sound dynamics="31" />
      </direction>
      <note>
        <rest measure="yes" />
        <duration>30240</duration>
      </note>
      <backup>
        <duration>30240</duration>
      </backup>
      <note print-object="no" print-spacing="yes">
        <rest measure="yes" />
        <duration>30240</duration>
        <voice>6</voice>
      </note>
      <backup>
        <duration>30240</duration>
      </backup>
      <note print-object="no" print-spacing="yes">
        <rest measure="yes" />
        <duration>30240</duration>
        <voice>7</voice>
      </note>
    </measure>
    
    <measure implicit="no" number="2">
      <note>
        <rest measure="yes" />
        <duration>30240</duration>
      </note>
      <backup>
        <duration>30240</duration>
      </backup>
      <note print-object="no" print-spacing="yes">
        <rest measure="yes" />
        <duration>30240</duration>
        <voice>6</voice>
      </note>
      <backup>
        <duration>30240</duration>
      </backup>
      <note print-object="no" print-spacing="yes">
        <rest measure="yes" />
        <duration>30240</duration>
        <voice>7</voice>
      </note>
    </measure>
    
    <measure implicit="no" number="3">
      <note>
        <rest measure="yes" />
        <duration>30240</duration>
      </note>
      <backup>
        <duration>30240</duration>
      </backup>
      <note print-object="no" print-spacing="yes">
        <rest measure="yes" />
        <duration>30240</duration>
        <voice>6</voice>
      </note>
      <backup>
        <duration>30240</duration>
      </backup>
      <note print-object="no" print-spacing="yes">
        <rest measure="yes" />
        <duration>30240</duration>
        <voice>7</voice>
      </note>
    </measure>
    
    <measure implicit="no" number="4">
      <note>
        <rest measure="yes" />
        <duration>30240</duration>
      </note>
      <backup>
        <duration>30240</duration>
      </backup>
      <note print-object="no" print-spacing="yes">
        <rest measure="yes" />
        <duration>30240</duration>
        <voice>6</voice>
      </note>
      <backup>
        <duration>30240</duration>
      </backup>
      <note print-object="no" print-spacing="yes">
        <rest measure="yes" />
        <duration>30240</duration>
        <voice>7</voice>
      </note>
    </measure>
    
    <measure implicit="no" number="5">
      <note>
        <rest />
        <duration>10080</duration>
        <type>quarter</type>
      </note>
      <note default-x="71.15" default-y="0">
        <pitch>
          <step>F</step>
          <alter>1</alter>
          <octave>5</octave>
        </pitch>
        <duration>10080</duration>
        <staff>1</staff><type>quarter</type>
        <stem>down</stem>
      </note>
      <direction placement="below">
        <direction-type>
          <dynamics default-x="3.25" default-y="-40" relative-x="-8.88" relative-y="-22.75">
            <pp />
          </dynamics>
        </direction-type>
        <offset sound="yes">-10080</offset>
        <sound dynamics="31" />
      </direction>
      <note default-x="130.31" default-y="10">
        <pitch>
          <step>A</step>
          <octave>5</octave>
        </pitch>
        <duration>10080</duration>
        <staff>1</staff><type>quarter</type>
        <stem>down</stem>
      </note>
      <backup>
        <duration>30240</duration>
      </backup>
      <note print-object="no" print-spacing="yes">
        <rest measure="yes" />
        <duration>30240</duration>
        <voice>6</voice>
      </note>
      <backup>
        <duration>30240</duration>
      </backup>
      <note print-object="no" print-spacing="yes">
        <rest measure="yes" />
        <duration>30240</duration>
        <voice>7</voice>
      </note>
    </measure>
    
    <measure implicit="no" number="6">
      <print new-system="yes">
        <system-layout>
          <system-margins>
            <left-margin>13.8</left-margin>
            <right-margin>0</right-margin>
          </system-margins>
          <system-distance>108.58</system-distance>
        </system-layout>
        <staff-layout />
      </print>
      <attributes>
        <staff-details print-object="yes" />
      </attributes>
      <note default-x="93.02" default-y="5">
        <pitch>
          <step>G</step>
          <octave>5</octave>
        </pitch>
        <duration>10080</duration>
        <staff>1</staff><type>quarter</type>
        <stem>down</stem>
      </note>
      <note default-x="156.54" default-y="0">
        <pitch>
          <step>F</step>
          <alter>1</alter>
          <octave>5</octave>
        </pitch>
        <duration>10080</duration>
        <staff>1</staff><type>quarter</type>
        <stem>down</stem>
      </note>
      <note default-x="220.06" default-y="-15">
        <pitch>
          <step>C</step>
          <alter>1</alter>
          <octave>5</octave>
        </pitch>
        <duration>10080</duration>
        <staff>1</staff><type>quarter</type>
        <stem>down</stem>
      </note>
      <backup>
        <duration>30240</duration>
      </backup>
      <note print-object="no" print-spacing="yes">
        <rest measure="yes" />
        <duration>30240</duration>
        <voice>6</voice>
      </note>
      <backup>
        <duration>30240</duration>
      </backup>
      <note print-object="no" print-spacing="yes">
        <rest measure="yes" />
        <duration>30240</duration>
        <voice>7</voice>
      </note>
    </measure>
    
    <measure implicit="no" number="7">
      <note default-x="12" default-y="-20">
        <pitch>
          <step>B</step>
          <octave>4</octave>
        </pitch>
        <duration>10080</duration>
        <staff>1</staff><type>quarter</type>
        <stem>down</stem>
      </note>
      <note default-x="75.52" default-y="-15">
        <pitch>
          <step>C</step>
          <alter>1</alter>
          <octave>5</octave>
        </pitch>
        <duration>10080</duration>
        <staff>1</staff><type>quarter</type>
        <stem>down</stem>
      </note>
      <note default-x="139.04" default-y="-10">
        <pitch>
          <step>D</step>
          <octave>5</octave>
        </pitch>
        <duration>10080</duration>
        <staff>1</staff><type>quarter</type>
        <stem>down</stem>
      </note>
      <direction placement="below">
        <direction-type>
          <dynamics default-x="3.25" default-y="-40" relative-y="-40">
            <p />
          </dynamics>
        </direction-type>
        <offset sound="yes">-10080</offset>
        <sound dynamics="44" />
      </direction>
      <backup>
        <duration>30240</duration>
      </backup>
      <note print-object="no" print-spacing="yes">
        <rest measure="yes" />
        <duration>30240</duration>
        <voice>6</voice>
      </note>
      <backup>
        <duration>30240</duration>
      </backup>
      <note print-object="no" print-spacing="yes">
        <rest measure="yes" />
        <duration>30240</duration>
        <voice>7</voice>
      </note>
    </measure>
    
    <measure implicit="no" number="8">
      <note default-x="15.5" default-y="-25">
        <pitch>
          <step>A</step>
          <octave>4</octave>
        </pitch>
        <duration>30240</duration>
        <staff>1</staff><type>half</type>
        <dot />
        <stem>up</stem>
      </note>
      <backup>
        <duration>30240</duration>
      </backup>
      <note print-object="no" print-spacing="yes">
        <rest measure="yes" />
        <duration>30240</duration>
        <voice>6</voice>
      </note>
      <backup>
        <duration>30240</duration>
      </backup>
      <note print-object="no" print-spacing="yes">
        <rest measure="yes" />
        <duration>30240</duration>
        <voice>7</voice>
      </note>
    </measure>
    
    <measure implicit="no" number="9">
      <direction placement="below">
        <direction-type>
          <dynamics default-x="6.5" default-y="-40" relative-y="-40">
            <pp />
          </dynamics>
        </direction-type>
        <sound dynamics="31" />
      </direction>
      <note default-x="12" default-y="-35">
        <pitch>
          <step>F</step>
          <alter>1</alter>
          <octave>4</octave>
        </pitch>
        <duration>30240</duration>
        <staff>1</staff><tie type="start" />
        <type>half</type>
        <dot />
        <stem>up</stem>
        <notations>
          <tied type="start" />
        </notations>
      </note>
      <direction placement="above">
        <direction-type>
          <dynamics default-x="6.5" default-y="-80" relative-x="-15.55" relative-y="39.1">
            <f />
          </dynamics>
        </direction-type>
        <offset sound="yes">-20160</offset>
        <sound dynamics="88" />
      </direction>
      <backup>
        <duration>30240</duration>
      </backup>
      <note print-object="no" print-spacing="yes">
        <rest measure="yes" />
        <duration>30240</duration>
        <voice>6</voice>
      </note>
      <backup>
        <duration>30240</duration>
      </backup>
      <note print-object="no" print-spacing="yes">
        <rest measure="yes" />
        <duration>30240</duration>
        <voice>7</voice>
      </note>
    </measure>
    
    <measure implicit="no" number="10">
      <direction placement="below">
        <direction-type>
          <dynamics default-x="6.5" default-y="-40" relative-y="-40">
            <pp />
          </dynamics>
        </direction-type>
        <sound dynamics="31" />
      </direction>
      <note default-x="15.5" default-y="-35">
        <pitch>
          <step>F</step>
          <alter>1</alter>
          <octave>4</octave>
        </pitch>
        <duration>30240</duration>
        <staff>1</staff><tie type="stop" />
        <tie type="start" />
        <type>half</type>
        <dot />
        <stem>up</stem>
        <notations>
          <tied type="stop" />
          <tied type="start" />
        </notations>
      </note>
      <backup>
        <duration>30240</duration>
      </backup>
      <note print-object="no" print-spacing="yes">
        <rest measure="yes" />
        <duration>30240</duration>
        <voice>6</voice>
      </note>
      <backup>
        <duration>30240</duration>
      </backup>
      <note print-object="no" print-spacing="yes">
        <rest measure="yes" />
        <duration>30240</duration>
        <voice>7</voice>
      </note>
    </measure>
    
    <measure implicit="no" number="11">
      <print new-system="yes">
        <system-layout>
          <system-margins>
            <left-margin>13.8</left-margin>
            <right-margin>0</right-margin>
          </system-margins>
          <system-distance>108.58</system-distance>
        </system-layout>
        <staff-layout />
      </print>
      <attributes>
        <staff-details print-object="yes" />
      </attributes>
      <note default-x="89.52" default-y="-35">
        <pitch>
          <step>F</step>
          <alter>1</alter>
          <octave>4</octave>
        </pitch>
        <duration>30240</duration>
        <staff>1</staff><tie type="stop" />
        <tie type="start" />
        <type>half</type>
        <dot />
        <stem>up</stem>
        <notations>
          <tied type="stop" />
          <tied type="start" />
        </notations>
      </note>
      <backup>
        <duration>30240</duration>
      </backup>
      <note print-object="no" print-spacing="yes">
        <rest measure="yes" />
        <duration>30240</duration>
        <voice>6</voice>
      </note>
      <backup>
        <duration>30240</duration>
      </backup>
      <note print-object="no" print-spacing="yes">
        <rest measure="yes" />
        <duration>30240</duration>
        <voice>7</voice>
      </note>
    </measure>
    
    <measure implicit="no" number="12">
      <note default-x="15.5" default-y="-35">
        <pitch>
          <step>F</step>
          <alter>1</alter>
          <octave>4</octave>
        </pitch>
        <duration>30240</duration>
        <staff>1</staff><tie type="stop" />
        <type>half</type>
        <dot />
        <stem>up</stem>
        <notations>
          <tied type="stop" />
        </notations>
      </note>
      <backup>
        <duration>30240</duration>
      </backup>
      <note print-object="no" print-spacing="yes">
        <rest measure="yes" />
        <duration>30240</duration>
        <voice>6</voice>
      </note>
      <backup>
        <duration>30240</duration>
      </backup>
      <note print-object="no" print-spacing="yes">
        <rest measure="yes" />
        <duration>30240</duration>
        <voice>7</voice>
      </note>
    </measure>
    
    <measure implicit="no" number="13">
      <direction placement="below">
        <direction-type>
          <dynamics default-x="4.7" default-y="-49.14" relative-x="21.37" relative-y="-28.83">
            <pp />
          </dynamics>
        </direction-type>
        <sound dynamics="31" />
      </direction>
      <note>
        <rest />
        <duration>10080</duration>
        <type>quarter</type>
      </note>
      <note default-x="74.72" default-y="0">
        <pitch>
          <step>F</step>
          <alter>1</alter>
          <octave>5</octave>
        </pitch>
        <duration>10080</duration>
        <staff>1</staff><type>quarter</type>
        <stem>down</stem>
      </note>
      <note default-x="137.45" default-y="10">
        <pitch>
          <step>A</step>
          <octave>5</octave>
        </pitch>
        <duration>10080</duration>
        <staff>1</staff><type>quarter</type>
        <stem>down</stem>
      </note>
      <backup>
        <duration>30240</duration>
      </backup>
      <note print-object="no" print-spacing="yes">
        <rest measure="yes" />
        <duration>30240</duration>
        <voice>6</voice>
      </note>
      <backup>
        <duration>30240</duration>
      </backup>
      <note print-object="no" print-spacing="yes">
        <rest measure="yes" />
        <duration>30240</duration>
        <voice>7</voice>
      </note>
    </measure>
    
    <measure implicit="no" number="14">
      <note default-x="15.5" default-y="5">
        <pitch>
          <step>G</step>
          <octave>5</octave>
        </pitch>
        <duration>10080</duration>
        <staff>1</staff><type>quarter</type>
        <stem>down</stem>
      </note>
      <note default-x="78.22" default-y="0">
        <pitch>
          <step>F</step>
          <alter>1</alter>
          <octave>5</octave>
        </pitch>
        <duration>10080</duration>
        <staff>1</staff><type>quarter</type>
        <stem>down</stem>
      </note>
      <note default-x="140.95" default-y="-15">
        <pitch>
          <step>C</step>
          <alter>1</alter>
          <octave>5</octave>
        </pitch>
        <duration>10080</duration>
        <staff>1</staff><type>quarter</type>
        <stem>down</stem>
      </note>
      <backup>
        <duration>30240</duration>
      </backup>
      <note print-object="no" print-spacing="yes">
        <rest measure="yes" />
        <duration>30240</duration>
        <voice>6</voice>
      </note>
      <backup>
        <duration>30240</duration>
      </backup>
      <note print-object="no" print-spacing="yes">
        <rest measure="yes" />
        <duration>30240</duration>
        <voice>7</voice>
      </note>
    </measure>
    
    <measure implicit="no" number="15">
      <note default-x="12" default-y="-20">
        <pitch>
          <step>B</step>
          <octave>4</octave>
        </pitch>
        <duration>10080</duration>
        <staff>1</staff><type>quarter</type>
        <stem>down</stem>
      </note>
      <note default-x="137.45" default-y="-10">
        <pitch>
          <step>D</step>
          <octave>5</octave>
        </pitch>
        <duration>10080</duration>
        <staff>1</staff><type>quarter</type>
        <stem>down</stem>
      </note>
      <note default-x="74.72" default-y="-15">
        <pitch>
          <step>C</step>
          <alter>1</alter>
          <octave>5</octave>
        </pitch>
        <duration>10080</duration>
        <staff>1</staff><type>quarter</type>
        <stem>down</stem>
      </note>
      <backup>
        <duration>30240</duration>
      </backup>
      <note print-object="no" print-spacing="yes">
        <rest measure="yes" />
        <duration>30240</duration>
        <voice>6</voice>
      </note>
      <backup>
        <duration>30240</duration>
      </backup>
      <note print-object="no" print-spacing="yes">
        <rest measure="yes" />
        <duration>30240</duration>
        <voice>7</voice>
      </note>
    </measure>
    
    <measure implicit="no" number="16">
      <print new-system="yes">
        <system-layout>
          <system-margins>
            <left-margin>13.8</left-margin>
            <right-margin>0</right-margin>
          </system-margins>
          <system-distance>108.58</system-distance>
        </system-layout>
        <staff-layout />
      </print>
      <attributes>
        <staff-details print-object="yes" />
      </attributes>
      <direction placement="below">
        <direction-type>
          <dynamics default-x="6.5" default-y="-40" relative-y="-40">
            <p />
          </dynamics>
        </direction-type>
        <sound dynamics="44" />
      </direction>
      <note default-x="93.02" default-y="-25">
        <pitch>
          <step>A</step>
          <octave>4</octave>
        </pitch>
        <duration>30240</duration>
        <staff>1</staff><type>half</type>
        <dot />
        <stem>up</stem>
      </note>
      <backup>
        <duration>30240</duration>
      </backup>
      <note print-object="no" print-spacing="yes">
        <rest measure="yes" />
        <duration>30240</duration>
        <voice>6</voice>
      </note>
      <backup>
        <duration>30240</duration>
      </backup>
      <note print-object="no" print-spacing="yes">
        <rest measure="yes" />
        <duration>30240</duration>
        <voice>7</voice>
      </note>
    </measure>
  </part>
</score-partwise>