{
  "notes": [
    {
      "pitch": 71,
      "startTime": 0.6111040000000116,
      "endTime": 1.7222150000000056,
      "velocity": 0.49606299212598426
    },
    {
      "pitch": 72,
      "startTime": 1.7222150000000056,
      "endTime": 2.8333259999999996,
      "velocity": 0.49606299212598426
    },
    {
      "pitch": 76,
      "startTime": 2.8333259999999996,
      "endTime": 3.9444370000000077,
      "velocity": 0.49606299212598426
    },
    {
      "pitch": 74,
      "startTime": 3.9444370000000077,
      "endTime": 5.055548000000002,
      "velocity": 0.49606299212598426
    },
    {
      "pitch": 71,
      "startTime": 5.055548000000002,
      "endTime": 6.16665900000001,
      "velocity": 0.49606299212598426
    }
  ],
  "totalTime": 6.16665900000001,
  "tempos": [
    {
      "time": 0.0,
      "qpm": 120.0
    }
  ],
  "timeSignatures": [
    {
      "time": 0.0,
      "numerator": 3,
      "denominator": 4
    }
  ]
}